azure/search/documents/__init__.py
azure/search/documents/_api_versions.py
azure/search/documents/_headers_mixin.py
azure/search/documents/_index_documents_batch.py
azure/search/documents/_paging.py
azure/search/documents/_queries.py
azure/search/documents/_search_client.py
azure/search/documents/_search_documents_error.py
azure/search/documents/_search_indexing_buffered_sender.py
azure/search/documents/_search_indexing_buffered_sender_base.py
azure/search/documents/_utils.py
azure/search/documents/_version.py
azure/search/documents/py.typed
azure/search/documents/_generated/__init__.py
azure/search/documents/_generated/_configuration.py
azure/search/documents/_generated/_patch.py
azure/search/documents/_generated/_search_index_client.py
azure/search/documents/_generated/_serialization.py
azure/search/documents/_generated/py.typed
azure/search/documents/_generated/aio/__init__.py
azure/search/documents/_generated/aio/_configuration.py
azure/search/documents/_generated/aio/_patch.py
azure/search/documents/_generated/aio/_search_index_client.py
azure/search/documents/_generated/aio/operations/__init__.py
azure/search/documents/_generated/aio/operations/_documents_operations.py
azure/search/documents/_generated/aio/operations/_patch.py
azure/search/documents/_generated/models/__init__.py
azure/search/documents/_generated/models/_models_py3.py
azure/search/documents/_generated/models/_patch.py
azure/search/documents/_generated/models/_search_index_client_enums.py
azure/search/documents/_generated/operations/__init__.py
azure/search/documents/_generated/operations/_documents_operations.py
azure/search/documents/_generated/operations/_patch.py
azure/search/documents/aio/__init__.py
azure/search/documents/aio/_index_documents_batch_async.py
azure/search/documents/aio/_paging.py
azure/search/documents/aio/_search_client_async.py
azure/search/documents/aio/_search_indexing_buffered_sender_async.py
azure/search/documents/aio/_timer.py
azure_search_documents-11.5.1.dist-info/LICENSE
azure_search_documents-11.5.1.dist-info/METADATA
azure_search_documents-11.5.1.dist-info/WHEEL
azure_search_documents-11.5.1.dist-info/top_level.txt
azure_search_documents-11.5.1.dist-info/RECORD
