Metadata-Version: 2.1
Name: azure-search-documents
Version: 11.5.1
Summary: Microsoft Azure Cognitive Search Client Library for Python
Home-page: https://github.com/Azure/azure-sdk-for-python/tree/main/sdk/search/azure-search-documents
Author: Microsoft Corporation
Author-email: ascl@microsoft.com
License: MIT License
Keywords: azure,azure sdk
Classifier: Development Status :: 5 - Production/Stable
Classifier: Programming Language :: Python
Classifier: Programming Language :: Python :: 3 :: Only
Classifier: Programming Language :: Python :: 3
Classifier: Programming Language :: Python :: 3.8
Classifier: Programming Language :: Python :: 3.9
Classifier: Programming Language :: Python :: 3.10
Classifier: Programming Language :: Python :: 3.11
Classifier: Programming Language :: Python :: 3.12
Classifier: License :: OSI Approved :: MIT License
Requires-Python: >=3.8
License-File: LICENSE
Requires-Dist: azure-core>=1.28.0
Requires-Dist: azure-common>=1.1
Requires-Dist: isodate>=0.6.0
Requires-Dist: typing-extensions>=4.6.0
